{
	"id": "794dc435-79de-41d1-a789-89fb1b226c5c",
	"name": "cc-local",
	"values": [
		{
			"key": "IP",
			"value": "localhost",
			"type": "default",
			"enabled": true
		},
		{
			"key": "PORT",
			"value": "8035",
			"type": "default",
			"enabled": true
		},
		{
			"key": "USER",
			"value": "admin",
			"type": "default",
			"enabled": true
		},
		{
			"key": "PASS",
			"value": "admin1234",
			"type": "default",
			"enabled": true
		},
		{
			"key": "ACCESS_TOKEN",
			"value": "",
			"type": "default",
			"enabled": true
		}
	],
	"_postman_variable_scope": "environment",
	"_postman_exported_at": "2023-04-04T01:18:10.630Z",
	"_postman_exported_using": "Postman/10.12.0"
}